pdm_project_demo-0.1.0.dist-info/METADATA
pdm_project_demo-0.1.0.dist-info/WHEEL
pdm_project_demo/__init__.py
pdm_project_demo/main.py
pdm_project_demo-0.1.0.dist-info/RECORD
