Metadata-Version: 2.1
Name: pdm_project_demo
Version: 0.1.0
Summary: pdm project demo
Author-Email: zhou402981948 <402981948@qq.com>
License: MIT
Requires-Python: >=3.10
Requires-Dist: fastapi>=0.111.1
